mplusa/__init__.py
mplusa/maxplus.py
mplusa/minplus.py
mplusa-0.0.2.dist-info/LICENSE
mplusa-0.0.2.dist-info/METADATA
mplusa-0.0.2.dist-info/WHEEL
mplusa-0.0.2.dist-info/top_level.txt
mplusa-0.0.2.dist-info/RECORD
