Metadata-Version: 2.2
Name: mplusa
Version: 0.0.2
Summary: A library for calculations in tropical and arctic semirings.
Author-email: "Maksymilian W." <maksymilian3563@gmail.com>
License: Copyright (c) 2025 Maksymilian Wiekiera
Project-URL: homepage, https://github.com/Hadelekw/mplusa
Classifier: Programming Language :: Python :: 3
Classifier: Operating System :: OS Independent
Requires-Python: >=3.11
License-File: LICENSE
Requires-Dist: numpy>=2.2.3
